compmech-0.8.0.dist-info/LICENSE
compmech-0.8.0.dist-info/METADATA
compmech-0.8.0.dist-info/RECORD
compmech-0.8.0.dist-info/top_level.txt
compmech-0.8.0.dist-info/WHEEL
compmech-0.8.0.data/data/LICENSE
compmech-0.8.0.data/data/README.md
compmech-0.8.0.data/data/setup.py
compmech-0.8.0.data/data/version.py
compmech-0.8.0.data/data/ROADMAP.rst
compmech.libs/libgomp-a34b3233.so.1.0.0
compmech/interpolate.py
compmech/setup_patch.py
compmech/logger.py
compmech/__init__.py
compmech/constants.py
compmech/sparse.py
compmech/version.py
compmech/composite/laminate.py
compmech/composite/__init__.py
compmech/composite/lamina.py
compmech/composite/matlamina.py
compmech/stiffener/bladestiff2d.py
compmech/stiffener/bladestiff1d.py
compmech/stiffener/__init__.py
compmech/stiffener/tstiff2d.py
compmech/stiffener/modelDB.py
compmech/stiffener/models/bladestiff2d_clt_donnell_bardell.cpython-38-x86_64-linux-gnu.so
compmech/stiffener/models/__init__.py
compmech/stiffener/models/tstiff2d_clt_donnell_bardell.cpython-38-x86_64-linux-gnu.so
compmech/stiffener/models/bladestiff1d_clt_donnell_bardell.cpython-38-x86_64-linux-gnu.so
compmech/conecyl/studies.py
compmech/conecyl/test.py
compmech/conecyl/conecyl.py
compmech/conecyl/plotutils.py
compmech/conecyl/__init__.py
compmech/conecyl/dev_utils.py
compmech/conecyl/conecylDB.py
compmech/conecyl/modelDB.py
compmech/conecyl/fsdt/fsdt_donnell_bc3_nonlinear.cpython-38-x86_64-linux-gnu.so
compmech/conecyl/fsdt/fsdt_donnell_bc4_nonlinear.cpython-38-x86_64-linux-gnu.so
compmech/conecyl/fsdt/fsdt_shadmehri2012_bc3.cpython-38-x86_64-linux-gnu.so
compmech/conecyl/fsdt/fsdt_donnell_bcn_linear.cpython-38-x86_64-linux-gnu.so
compmech/conecyl/fsdt/fsdt_commons_bcn.cpython-38-x86_64-linux-gnu.so
compmech/conecyl/fsdt/__init__.py
compmech/conecyl/fsdt/fsdt_donnell_bc2_nonlinear.cpython-38-x86_64-linux-gnu.so
compmech/conecyl/fsdt/fsdt_commons_bc2.cpython-38-x86_64-linux-gnu.so
compmech/conecyl/fsdt/fsdt_commons_bc3.cpython-38-x86_64-linux-gnu.so
compmech/conecyl/fsdt/fsdt_donnell_bcn_nonlinear.cpython-38-x86_64-linux-gnu.so
