Metadata-Version: 2.1
Name: compmech
Version: 0.8.0
Summary: CompMech: Computational Mechanics in Python
Home-page: http://saullocastro.github.io/compmech/
Download-URL: https://github.com/saullocastro/compmech/releases
Author: Saullo G. P. Castro
Author-email: S.G.P.Castro@tudelft.nl
License: BSD
Keywords: computational,mechanics,structural,analysis,analytical,Bardell,Ritz
Classifier: Development Status :: 4 - Beta
Classifier: Intended Audience :: Science/Research
Classifier: Intended Audience :: Developers
Classifier: Intended Audience :: Education
Classifier: Intended Audience :: End Users/Desktop
Classifier: Topic :: Scientific/Engineering
Classifier: Topic :: Scientific/Engineering :: Mathematics
Classifier: Topic :: Education
Classifier: Topic :: Software Development
Classifier: Topic :: Software Development :: Libraries :: Python Modules
Classifier: Operating System :: Microsoft :: Windows
Classifier: Operating System :: Unix
Classifier: Operating System :: POSIX :: BSD
Classifier: Programming Language :: Fortran
Classifier: Programming Language :: C
Classifier: Programming Language :: Python :: 3.8
Classifier: Programming Language :: Python :: 3.9
Classifier: Programming Language :: Python :: 3.10
Classifier: Programming Language :: Python :: 3.11
Classifier: License :: OSI Approved :: BSD License
License-File: LICENSE
Requires-Dist: numpy
Requires-Dist: scipy
Requires-Dist: matplotlib
